sentinel2_geodes/__init__.py
sentinel2_geodes/cli.py
sentinel2_geodes/core/__init__.py
sentinel2_geodes/core/downloader.py
sentinel2_geodes/core/processor.py
sentinel2_geodes/core/search.py
sentinel2_geodes/processing/__init__.py
sentinel2_geodes/processing/band_math.py
sentinel2_geodes/processing/cropper.py
sentinel2_geodes/utils/__init__.py
sentinel2_geodes/utils/config.py
sentinel2_geodes/utils/logger.py
sentinel2_geodes-0.1.0.dist-info/METADATA
sentinel2_geodes-0.1.0.dist-info/WHEEL
sentinel2_geodes-0.1.0.dist-info/entry_points.txt
sentinel2_geodes-0.1.0.dist-info/licenses/LICENSE
sentinel2_geodes-0.1.0.dist-info/RECORD
