Metadata-Version: 2.4
Name: sentinel2-geodes
Version: 0.1.0
Summary: A Python package for searching, downloading, and processing Sentinel-2 satellite imagery from the GEODES portal
Project-URL: Homepage, https://github.com/Adam-serghini/sentinel2-geodes
Project-URL: Documentation, https://sentinel2-geodes.readthedocs.io
Project-URL: Repository, https://github.com/Adam-serghini/sentinel2-geodes
Project-URL: Issues, https://github.com/Adam-serghini/sentinel2-geodes/issues
Author-email: Adam Serghini <serghini.adam.84@gmail.com>
License: MIT
License-File: LICENSE
Keywords: earth-observation,geodes,ndvi,remote-sensing,satellite,sentinel-2
Classifier: Development Status :: 3 - Alpha
Classifier: Intended Audience :: Science/Research
Classifier: License :: OSI Approved :: MIT License
Classifier: Programming Language :: Python :: 3
Classifier: Programming Language :: Python :: 3.9
Classifier: Programming Language :: Python :: 3.10
Classifier: Programming Language :: Python :: 3.11
Classifier: Programming Language :: Python :: 3.12
Classifier: Topic :: Scientific/Engineering :: GIS
Requires-Python: >=3.9
Requires-Dist: click>=8.1.0
Requires-Dist: geopandas>=0.14.0
Requires-Dist: pandas>=2.0.0
Requires-Dist: pydantic>=2.0.0
Requires-Dist: python-dotenv>=1.0.0
Requires-Dist: rasterio>=1.3.0
Requires-Dist: requests>=2.31.0
Requires-Dist: shapely>=2.0.0
Requires-Dist: tqdm>=4.66.0
Provides-Extra: dev
Requires-Dist: black>=23.0.0; extra == 'dev'
Requires-Dist: mypy>=1.5.0; extra == 'dev'
Requires-Dist: pre-commit>=3.4.0; extra == 'dev'
Requires-Dist: pytest-cov>=4.1.0; extra == 'dev'
Requires-Dist: pytest>=7.4.0; extra == 'dev'
Requires-Dist: ruff>=0.1.0; extra == 'dev'
Provides-Extra: docs
Requires-Dist: myst-parser>=2.0.0; extra == 'docs'
Requires-Dist: sphinx-rtd-theme>=1.3.0; extra == 'docs'
Requires-Dist: sphinx>=7.0.0; extra == 'docs'
Provides-Extra: viz
Requires-Dist: folium>=0.14.0; extra == 'viz'
Requires-Dist: matplotlib>=3.7.0; extra == 'viz'
Requires-Dist: plotly>=5.17.0; extra == 'viz'
